LICENSE
README.md
setup.py
dialectics/__init__.py
dialectics/dialectics.py
dialectics/imports.py
dialectics/intertxt.py
dialectics.egg-info/PKG-INFO
dialectics.egg-info/SOURCES.txt
dialectics.egg-info/dependency_links.txt
dialectics.egg-info/requires.txt
dialectics.egg-info/top_level.txt
dialectics/corpora/__init__.py
dialectics/corpora/corpus.py
dialectics/database/__init__.py
dialectics/database/baseobj.py
dialectics/database/docspace.py
dialectics/database/relspace.py
dialectics/models/__init__.py
dialectics/models/matching.py
dialectics/models/models.py
dialectics/models/networks.py
dialectics/texts/__init__.py
dialectics/texts/text.py
dialectics/texts/textlist.py
dialectics/utils/__init__.py
dialectics/utils/downloads.py
dialectics/utils/io.py
dialectics/utils/logs.py
dialectics/utils/misc.py
dialectics/utils/utils.py