Metadata-Version: 2.1
Name: dialectics
Version: 0.0.4
Summary: Code, data, and models to support dialectics as a weapon of thinking, analysis and action.
Home-page: https://github.com/deterritorial/dialectics.git
Author: Ryan Heuser
Author-email: rj416@cam.ac.uk
License: MIT
Platform: UNKNOWN
License-File: LICENSE
